altex/__init__.py
altex/charts.py
altex/data.py
altex-0.1.0.dist-info/METADATA
altex-0.1.0.dist-info/WHEEL
altex-0.1.0.dist-info/licenses/LICENSE
altex-0.1.0.dist-info/RECORD
