Metadata-Version: 2.4
Name: altex
Version: 0.1.0
Summary: A simple wrapper on top of Altair to make charts with an express API
Project-URL: Homepage, https://github.com/arnaudmiribel/altex
Project-URL: Bug Tracker, https://github.com/arnaudmiribel/altex/issues
Author-email: Arnaud Miribel <arnaudmiribel@gmail.com>
License-Expression: Apache-2.0
License-File: LICENSE
Keywords: altair,charts,python,streamlit,visualization
Requires-Python: <3.14,>=3.9
Requires-Dist: altair>=4.0.0
Requires-Dist: numpy>=1.19.0
Requires-Dist: pandas>=1.0.0
Requires-Dist: streamlit>=1.18.0
